__init__.py
ende.py
ende-0.1.dist-info/METADATA
ende-0.1.dist-info/WHEEL
ende-0.1.dist-info/entry_points.txt
ende-0.1.dist-info/top_level.txt
ende-0.1.dist-info/RECORD
